{
  "id": "bot_1776508518991_a1ku7o8dk",
  "date": "2026-04-18T10:35:18.991Z",
  "type": "bot",
  "whitePlayer": "Viktor",
  "blackPlayer": "Viktor",
  "opponent": "Viktor",
  "yourColor": "black",
  "result": "Loss",
  "resultReason": "Resignation",
  "moves": [],
  "pgn": "",
  "startFen": "rnbqkbnr/pppppppp/8/8/8/8/PPPPPPPP/RNBQKBNR w KQkq - 0 1",
  "endFen": "rnbqkbnr/pppppppp/8/8/8/8/PPPPPPPP/RNBQKBNR w KQkq - 0 1",
  "timeControl": "10+0",
  "duration": 4,
  "botName": "Viktor",
  "botRating": 400,
  "botLevel": "Regular",
  "botStyle": "Aggressive attacker",
  "totalMoves": 0,
  "displayName": "Black vs Viktor",
  "userEmail": "guest@123.cm"
}